packetdb.py
packetdb-0.0.1.dist-info/METADATA
packetdb-0.0.1.dist-info/WHEEL
packetdb-0.0.1.dist-info/top_level.txt
packetdb-0.0.1.dist-info/RECORD
